setup.py
MydistributionsMF89/Binomialdistribution.py
MydistributionsMF89/Gaussiandistribution.py
MydistributionsMF89/Generaldistribution.py
MydistributionsMF89/__init__.py
MydistributionsMF89.egg-info/PKG-INFO
MydistributionsMF89.egg-info/SOURCES.txt
MydistributionsMF89.egg-info/dependency_links.txt
MydistributionsMF89.egg-info/not-zip-safe
MydistributionsMF89.egg-info/top_level.txt